cloudshell/__init__.py
cloudshell/networking/__init__.py
cloudshell/networking/juniper/__init__.py
cloudshell/networking/juniper/autoload/__init__.py
cloudshell/networking/juniper/autoload/junos_generic_snmp_autoload.py
cloudshell/networking/juniper/autoload/utils.py
cloudshell/networking/juniper/autoload/generic/__init__.py
cloudshell/networking/juniper/autoload/generic/entities.py
cloudshell/networking/juniper/autoload/mibs/HCNUM-TC.json
cloudshell/networking/juniper/autoload/mibs/JUNIPER-CHASSIS-DEFINES-MIB.json
cloudshell/networking/juniper/autoload/mibs/JUNIPER-IF-MIB.json
cloudshell/networking/juniper/autoload/mibs/JUNIPER-L2CP-FEATURES-MIB.json
cloudshell/networking/juniper/autoload/mibs/JUNIPER-MIB.json
cloudshell/networking/juniper/autoload/mibs/JUNIPER-SMI.json
cloudshell/networking/juniper/autoload/snmp_tables/__init__.py
cloudshell/networking/juniper/autoload/snmp_tables/mibs_conf.py
cloudshell/networking/juniper/cli/__init__.py
cloudshell/networking/juniper/cli/juniper_cli_configurator.py
cloudshell/networking/juniper/cli/juniper_command_modes.py
cloudshell/networking/juniper/cli/juniper_ssh_session.py
cloudshell/networking/juniper/cli/juniper_telnet_session.py
cloudshell/networking/juniper/command_actions/__init__.py
cloudshell/networking/juniper/command_actions/add_remove_vlan_actions.py
cloudshell/networking/juniper/command_actions/commit_rollback_actions.py
cloudshell/networking/juniper/command_actions/enable_disable_snmp_actions.py
cloudshell/networking/juniper/command_actions/enable_disable_snmp_v3_actions.py
cloudshell/networking/juniper/command_actions/save_restore_actions.py
cloudshell/networking/juniper/command_actions/system_actions.py
cloudshell/networking/juniper/command_templates/__init__.py
cloudshell/networking/juniper/command_templates/add_remove_vlan.py
cloudshell/networking/juniper/command_templates/commit_rollback.py
cloudshell/networking/juniper/command_templates/enable_disable_snmp.py
cloudshell_networking_juniper-6.0.2.dist-info/METADATA
cloudshell_networking_juniper-6.0.2.dist-info/WHEEL
cloudshell_networking_juniper-6.0.2.dist-info/top_level.txt
cloudshell_networking_juniper-6.0.2.dist-info/RECORD
